colarise/__init__.py
colarise/back.py
colarise/colored.py
colarise/colors.py
colarise/fore.py
colarise/hex.py
colarise/style.py
colarise-3.3.1.dist-info/LICENSE.txt
colarise-3.3.1.dist-info/METADATA
colarise-3.3.1.dist-info/WHEEL
colarise-3.3.1.dist-info/top_level.txt
colarise-3.3.1.dist-info/RECORD
